README.md
setup.py
cookiedb_client.egg-info/PKG-INFO
cookiedb_client.egg-info/SOURCES.txt
cookiedb_client.egg-info/dependency_links.txt
cookiedb_client.egg-info/top_level.txt
cookiedbclient/__init__.py
cookiedbclient/client.py
cookiedbclient/dmp.py
cookiedbclient/exceptions.py