Metadata-Version: 2.1
Name: cookiedb-client
Version: 1.0.0
Summary: A client for manipulating CookieDB Server databases.
Home-page: https://github.com/jaedsonpys/cookiedb-client
Author: Jaedson Silva
Author-email: imunknowuser@protonmail.com
License: UNKNOWN
Project-URL: License, https://github.com/jaedsonpys/cookiedb-client/blob/master/LICENSE
Keywords: database,server,noSQL,cookiedb
Platform: UNKNOWN
Classifier: License :: OSI Approved :: GNU General Public License v3 (GPLv3)
Classifier: Development Status :: 5 - Production/Stable
Classifier: Intended Audience :: Developers
Classifier: Intended Audience :: System Administrators
Classifier: Intended Audience :: Science/Research
Classifier: Natural Language :: English
Classifier: Operating System :: OS Independent
Classifier: Programming Language :: Python :: 3
Classifier: Topic :: Database :: Database Engines/Servers
